matplotwave/__init__.py
matplotwave/mw.py
matplotwave-0.1.0.dist-info/licenses/LICENSE
matplotwave-0.1.0.dist-info/METADATA
matplotwave-0.1.0.dist-info/WHEEL
matplotwave-0.1.0.dist-info/top_level.txt
matplotwave-0.1.0.dist-info/RECORD
