Metadata-Version: 2.4
Name: matplotwave
Version: 0.1.0
Summary: A vaporwave-inspired color palette and theme extension for Matplotlib
Author: actopozipc
License: MIT
Project-URL: Homepage, https://github.com/actopozipc/matplotwave
Project-URL: Repository, https://github.com/actopozipc/matplotwave
Project-URL: Issues, https://github.com/actopozipc/matplotwave/issues
Classifier: License :: OSI Approved :: MIT License
Classifier: Programming Language :: Python :: 3
Classifier: Programming Language :: Python :: 3 :: Only
Classifier: Topic :: Scientific/Engineering :: Visualization
Requires-Python: >=3.8
License-File: LICENSE
Requires-Dist: matplotlib>=3.4
Requires-Dist: seaborn>=0.11
Requires-Dist: numpy>=1.20
Requires-Dist: pandas>=1.3
Dynamic: license-file
